<?xml version="1.0" ?>
<annotation>
  <folder>E:\spore\´ó°ßË¿ºÚËëÐâ²¡»ìºÏ\Annotations</folder>
  <filename>mixed_1419.jpg</filename>
  <size>
    <width>1920</width>
    <height>1200</height>
    <depth>3</depth>
  </size>
  <object>
    <name>dbb_spore</name>
    <pose>Unspecified</pose>
    <truncated>0</truncated>
    <difficult>0</difficult>
    <bndbox>
      <xmin>1081.237060546875</xmin>
      <ymin>612.1008911132812</ymin>
      <xmax>1149.7584228515625</xmax>
      <ymax>751.9356079101562</ymax>
    </bndbox>
  </object>
  <object>
    <name>dbb_spore</name>
    <pose>Unspecified</pose>
    <truncated>0</truncated>
    <difficult>0</difficult>
    <bndbox>
      <xmin>1594.244384765625</xmin>
      <ymin>1125.6004028320312</ymin>
      <xmax>1755.450439453125</xmax>
      <ymax>1191.5117797851562</ymax>
    </bndbox>
  </object>
  <object>
    <name>shs_spore</name>
    <pose>Unspecified</pose>
    <truncated>0</truncated>
    <difficult>0</difficult>
    <bndbox>
      <xmin>1442.9664916992188</xmin>
      <ymin>938.1463623046875</ymin>
      <xmax>1468.3848266601562</xmax>
      <ymax>964.3743896484375</ymax>
    </bndbox>
  </object>
  <object>
    <name>xb_spore</name>
    <pose>Unspecified</pose>
    <truncated>0</truncated>
    <difficult>0</difficult>
    <bndbox>
      <xmin>0.0</xmin>
      <ymin>1027.9713134765625</ymin>
      <xmax>21.078171730041504</xmax>
      <ymax>1076.5717163085938</ymax>
    </bndbox>
  </object>
  <object>
    <name>shs_spore</name>
    <pose>Unspecified</pose>
    <truncated>0</truncated>
    <difficult>0</difficult>
    <bndbox>
      <xmin>952.2144470214844</xmin>
      <ymin>1010.38916015625</ymin>
      <xmax>975.9723815917969</xmax>
      <ymax>1033.7199096679688</ymax>
    </bndbox>
  </object>
  <object>
    <name>shs_spore</name>
    <pose>Unspecified</pose>
    <truncated>0</truncated>
    <difficult>0</difficult>
    <bndbox>
      <xmin>751.4991760253906</xmin>
      <ymin>110.17584228515625</ymin>
      <xmax>775.5325012207031</xmax>
      <ymax>133.22003173828125</ymax>
    </bndbox>
  </object>
  <object>
    <name>dbb_spore</name>
    <pose>Unspecified</pose>
    <truncated>0</truncated>
    <difficult>0</difficult>
    <bndbox>
      <xmin>420.22869873046875</xmin>
      <ymin>373.5724182128906</ymin>
      <xmax>465.9862060546875</xmax>
      <ymax>551.2724304199219</ymax>
    </bndbox>
  </object>
  <object>
    <name>dbb_spore</name>
    <pose>Unspecified</pose>
    <truncated>0</truncated>
    <difficult>0</difficult>
    <bndbox>
      <xmin>1440.5051879882812</xmin>
      <ymin>583.2978515625</ymin>
      <xmax>1616.3735961914062</xmax>
      <ymax>630.5249633789062</ymax>
    </bndbox>
  </object>
  <object>
    <name>shs_spore</name>
    <pose>Unspecified</pose>
    <truncated>0</truncated>
    <difficult>0</difficult>
    <bndbox>
      <xmin>931.2266235351562</xmin>
      <ymin>1008.0414733886719</ymin>
      <xmax>951.9761352539062</xmax>
      <ymax>1031.1041564941406</ymax>
    </bndbox>
  </object>
  <object>
    <name>shs_spore</name>
    <pose>Unspecified</pose>
    <truncated>0</truncated>
    <difficult>0</difficult>
    <bndbox>
      <xmin>450.4382629394531</xmin>
      <ymin>929.0182800292969</ymin>
      <xmax>469.7227478027344</xmax>
      <ymax>948.8161926269531</ymax>
    </bndbox>
  </object>
</annotation>
