<?xml version="1.0" ?>
<annotation>
  <folder>E:\spore\´ó°ßË¿ºÚËëÐâ²¡»ìºÏ\Annotations</folder>
  <filename>mixed_1173.jpg</filename>
  <size>
    <width>1920</width>
    <height>1200</height>
    <depth>3</depth>
  </size>
  <object>
    <name>shs_spore</name>
    <pose>Unspecified</pose>
    <truncated>0</truncated>
    <difficult>0</difficult>
    <bndbox>
      <xmin>1172.3653564453125</xmin>
      <ymin>701.861572265625</ymin>
      <xmax>1195.60107421875</xmax>
      <ymax>724.0805053710938</ymax>
    </bndbox>
  </object>
  <object>
    <name>shs_spore</name>
    <pose>Unspecified</pose>
    <truncated>0</truncated>
    <difficult>0</difficult>
    <bndbox>
      <xmin>1697.0502319335938</xmin>
      <ymin>210.3654327392578</ymin>
      <xmax>1720.8550415039062</xmax>
      <ymax>233.4067840576172</ymax>
    </bndbox>
  </object>
  <object>
    <name>dbb_spore</name>
    <pose>Unspecified</pose>
    <truncated>0</truncated>
    <difficult>0</difficult>
    <bndbox>
      <xmin>1058.5969848632812</xmin>
      <ymin>1042.6078491210938</ymin>
      <xmax>1097.9100952148438</xmax>
      <ymax>1127.8903198242188</ymax>
    </bndbox>
  </object>
  <object>
    <name>shs_spore</name>
    <pose>Unspecified</pose>
    <truncated>0</truncated>
    <difficult>0</difficult>
    <bndbox>
      <xmin>1179.6983642578125</xmin>
      <ymin>1079.6290283203125</ymin>
      <xmax>1201.4945068359375</xmax>
      <ymax>1100.946533203125</ymax>
    </bndbox>
  </object>
  <object>
    <name>dbb_spore</name>
    <pose>Unspecified</pose>
    <truncated>0</truncated>
    <difficult>0</difficult>
    <bndbox>
      <xmin>1214.1632080078125</xmin>
      <ymin>893.8662414550781</ymin>
      <xmax>1267.307373046875</xmax>
      <ymax>1065.6327209472656</ymax>
    </bndbox>
  </object>
  <object>
    <name>shs_spore</name>
    <pose>Unspecified</pose>
    <truncated>0</truncated>
    <difficult>0</difficult>
    <bndbox>
      <xmin>1683.8289184570312</xmin>
      <ymin>597.2704467773438</ymin>
      <xmax>1708.2182006835938</xmax>
      <ymax>620.2252807617188</ymax>
    </bndbox>
  </object>
  <object>
    <name>shs_spore</name>
    <pose>Unspecified</pose>
    <truncated>0</truncated>
    <difficult>0</difficult>
    <bndbox>
      <xmin>1384.8511962890625</xmin>
      <ymin>705.2537841796875</ymin>
      <xmax>1406.011962890625</xmax>
      <ymax>726.68408203125</ymax>
    </bndbox>
  </object>
  <object>
    <name>shs_spore</name>
    <pose>Unspecified</pose>
    <truncated>0</truncated>
    <difficult>0</difficult>
    <bndbox>
      <xmin>1215.9819946289062</xmin>
      <ymin>124.16061401367188</ymin>
      <xmax>1237.6600341796875</xmax>
      <ymax>145.15438842773438</ymax>
    </bndbox>
  </object>
  <object>
    <name>shs_spore</name>
    <pose>Unspecified</pose>
    <truncated>0</truncated>
    <difficult>0</difficult>
    <bndbox>
      <xmin>736.0341796875</xmin>
      <ymin>635.0850219726562</ymin>
      <xmax>760.7546081542969</xmax>
      <ymax>658.8012084960938</ymax>
    </bndbox>
  </object>
  <object>
    <name>shs_spore</name>
    <pose>Unspecified</pose>
    <truncated>0</truncated>
    <difficult>0</difficult>
    <bndbox>
      <xmin>501.42041015625</xmin>
      <ymin>666.5916137695312</ymin>
      <xmax>520.4939575195312</xmax>
      <ymax>685.070068359375</ymax>
    </bndbox>
  </object>
  <object>
    <name>shs_spore</name>
    <pose>Unspecified</pose>
    <truncated>0</truncated>
    <difficult>0</difficult>
    <bndbox>
      <xmin>1584.4118041992188</xmin>
      <ymin>659.1925048828125</ymin>
      <xmax>1606.3807983398438</xmax>
      <ymax>680.3983154296875</ymax>
    </bndbox>
  </object>
  <object>
    <name>shs_spore</name>
    <pose>Unspecified</pose>
    <truncated>0</truncated>
    <difficult>0</difficult>
    <bndbox>
      <xmin>851.1047973632812</xmin>
      <ymin>358.26548767089844</ymin>
      <xmax>871.8356323242188</xmax>
      <ymax>378.3603973388672</ymax>
    </bndbox>
  </object>
  <object>
    <name>shs_spore</name>
    <pose>Unspecified</pose>
    <truncated>0</truncated>
    <difficult>0</difficult>
    <bndbox>
      <xmin>611.3359222412109</xmin>
      <ymin>97.96943664550781</ymin>
      <xmax>633.4287872314453</xmax>
      <ymax>118.63792419433594</ymax>
    </bndbox>
  </object>
  <object>
    <name>dbb_spore</name>
    <pose>Unspecified</pose>
    <truncated>0</truncated>
    <difficult>0</difficult>
    <bndbox>
      <xmin>1431.17724609375</xmin>
      <ymin>305.0046844482422</ymin>
      <xmax>1576.6907958984375</xmax>
      <ymax>331.2539520263672</ymax>
    </bndbox>
  </object>
</annotation>
