<?xml version="1.0" ?>
<annotation>
  <folder>E:\spore\´ó°ßË¿ºÚËëÐâ²¡»ìºÏ\Annotations</folder>
  <filename>mixed_1709.jpg</filename>
  <size>
    <width>1920</width>
    <height>1200</height>
    <depth>3</depth>
  </size>
  <object>
    <name>dbb_spore</name>
    <pose>Unspecified</pose>
    <truncated>0</truncated>
    <difficult>0</difficult>
    <bndbox>
      <xmin>1024.786376953125</xmin>
      <ymin>45.102081298828125</ymin>
      <xmax>1140.302490234375</xmax>
      <ymax>165.59124755859375</ymax>
    </bndbox>
  </object>
  <object>
    <name>shs_spore</name>
    <pose>Unspecified</pose>
    <truncated>0</truncated>
    <difficult>0</difficult>
    <bndbox>
      <xmin>596.2922058105469</xmin>
      <ymin>211.38111877441406</ymin>
      <xmax>619.6980285644531</xmax>
      <ymax>233.77638244628906</ymax>
    </bndbox>
  </object>
  <object>
    <name>shs_spore</name>
    <pose>Unspecified</pose>
    <truncated>0</truncated>
    <difficult>0</difficult>
    <bndbox>
      <xmin>1150.9996948242188</xmin>
      <ymin>362.444091796875</ymin>
      <xmax>1173.2858276367188</xmax>
      <ymax>383.43475341796875</ymax>
    </bndbox>
  </object>
  <object>
    <name>dbb_spore</name>
    <pose>Unspecified</pose>
    <truncated>0</truncated>
    <difficult>0</difficult>
    <bndbox>
      <xmin>1299.791015625</xmin>
      <ymin>727.82373046875</ymin>
      <xmax>1364.4591064453125</xmax>
      <ymax>877.7340087890625</ymax>
    </bndbox>
  </object>
  <object>
    <name>dbb_spore</name>
    <pose>Unspecified</pose>
    <truncated>0</truncated>
    <difficult>0</difficult>
    <bndbox>
      <xmin>934.0330810546875</xmin>
      <ymin>970.349853515625</ymin>
      <xmax>976.62451171875</xmax>
      <ymax>1133.741455078125</ymax>
    </bndbox>
  </object>
  <object>
    <name>dbb_spore</name>
    <pose>Unspecified</pose>
    <truncated>0</truncated>
    <difficult>0</difficult>
    <bndbox>
      <xmin>754.1684875488281</xmin>
      <ymin>16.801986694335938</ymin>
      <xmax>794.4335632324219</xmax>
      <ymax>181.0682830810547</ymax>
    </bndbox>
  </object>
  <object>
    <name>shs_spore</name>
    <pose>Unspecified</pose>
    <truncated>0</truncated>
    <difficult>0</difficult>
    <bndbox>
      <xmin>2.2228317260742188</xmin>
      <ymin>1090.2412719726562</ymin>
      <xmax>25.173402786254883</xmax>
      <ymax>1113.5158081054688</ymax>
    </bndbox>
  </object>
  <object>
    <name>shs_spore</name>
    <pose>Unspecified</pose>
    <truncated>0</truncated>
    <difficult>0</difficult>
    <bndbox>
      <xmin>447.7138366699219</xmin>
      <ymin>774.8406372070312</ymin>
      <xmax>471.82672119140625</xmax>
      <ymax>796.1229858398438</ymax>
    </bndbox>
  </object>
  <object>
    <name>shs_spore</name>
    <pose>Unspecified</pose>
    <truncated>0</truncated>
    <difficult>0</difficult>
    <bndbox>
      <xmin>1598.499755859375</xmin>
      <ymin>9.8433837890625</ymin>
      <xmax>1621.768798828125</xmax>
      <ymax>33.00288391113281</ymax>
    </bndbox>
  </object>
  <object>
    <name>shs_spore</name>
    <pose>Unspecified</pose>
    <truncated>0</truncated>
    <difficult>0</difficult>
    <bndbox>
      <xmin>375.54039001464844</xmin>
      <ymin>323.39337158203125</ymin>
      <xmax>397.6630096435547</xmax>
      <ymax>345.50482177734375</ymax>
    </bndbox>
  </object>
  <object>
    <name>shs_spore</name>
    <pose>Unspecified</pose>
    <truncated>0</truncated>
    <difficult>0</difficult>
    <bndbox>
      <xmin>779.4510498046875</xmin>
      <ymin>581.2222595214844</ymin>
      <xmax>803.432373046875</xmax>
      <ymax>603.9786071777344</ymax>
    </bndbox>
  </object>
  <object>
    <name>dbb_spore</name>
    <pose>Unspecified</pose>
    <truncated>0</truncated>
    <difficult>0</difficult>
    <bndbox>
      <xmin>799.6051940917969</xmin>
      <ymin>245.76699829101562</ymin>
      <xmax>896.5068054199219</xmax>
      <ymax>275.6585998535156</ymax>
    </bndbox>
  </object>
  <object>
    <name>shs_spore</name>
    <pose>Unspecified</pose>
    <truncated>0</truncated>
    <difficult>0</difficult>
    <bndbox>
      <xmin>1210.9375</xmin>
      <ymin>253.125</ymin>
      <xmax>1234.375</xmax>
      <ymax>276.5625</ymax>
    </bndbox>
  </object>
</annotation>
