<?xml version="1.0" ?>
<annotation>
  <folder>E:\spore\´ó°ßË¿ºÚËëÐâ²¡»ìºÏ\Annotations</folder>
  <filename>mixed_1510.jpg</filename>
  <size>
    <width>1920</width>
    <height>1200</height>
    <depth>3</depth>
  </size>
  <object>
    <name>dbb_spore</name>
    <pose>Unspecified</pose>
    <truncated>0</truncated>
    <difficult>0</difficult>
    <bndbox>
      <xmin>482.4071044921875</xmin>
      <ymin>503.508544921875</ymin>
      <xmax>581.2237243652344</xmax>
      <ymax>629.8135986328125</ymax>
    </bndbox>
  </object>
  <object>
    <name>xb_spore</name>
    <pose>Unspecified</pose>
    <truncated>0</truncated>
    <difficult>0</difficult>
    <bndbox>
      <xmin>631.3187713623047</xmin>
      <ymin>757.4276733398438</ymin>
      <xmax>681.2670135498047</xmax>
      <ymax>801.5767822265625</ymax>
    </bndbox>
  </object>
  <object>
    <name>dbb_spore</name>
    <pose>Unspecified</pose>
    <truncated>0</truncated>
    <difficult>0</difficult>
    <bndbox>
      <xmin>1718.8370361328125</xmin>
      <ymin>729.0201416015625</ymin>
      <xmax>1792.6025390625</xmax>
      <ymax>886.1693115234375</ymax>
    </bndbox>
  </object>
  <object>
    <name>shs_spore</name>
    <pose>Unspecified</pose>
    <truncated>0</truncated>
    <difficult>0</difficult>
    <bndbox>
      <xmin>407.17291259765625</xmin>
      <ymin>211.40020751953125</ymin>
      <xmax>430.0976257324219</xmax>
      <ymax>233.38531494140625</ymax>
    </bndbox>
  </object>
  <object>
    <name>shs_spore</name>
    <pose>Unspecified</pose>
    <truncated>0</truncated>
    <difficult>0</difficult>
    <bndbox>
      <xmin>208.38711547851562</xmin>
      <ymin>92.59323120117188</ymin>
      <xmax>230.79107666015625</xmax>
      <ymax>112.97433471679688</ymax>
    </bndbox>
  </object>
  <object>
    <name>shs_spore</name>
    <pose>Unspecified</pose>
    <truncated>0</truncated>
    <difficult>0</difficult>
    <bndbox>
      <xmin>0.0</xmin>
      <ymin>388.300048828125</ymin>
      <xmax>18.37856912612915</xmax>
      <ymax>409.90850830078125</ymax>
    </bndbox>
  </object>
  <object>
    <name>shs_spore</name>
    <pose>Unspecified</pose>
    <truncated>0</truncated>
    <difficult>0</difficult>
    <bndbox>
      <xmin>334.8827362060547</xmin>
      <ymin>578.5235595703125</ymin>
      <xmax>359.4824981689453</xmax>
      <ymax>600.8360595703125</ymax>
    </bndbox>
  </object>
  <object>
    <name>shs_spore</name>
    <pose>Unspecified</pose>
    <truncated>0</truncated>
    <difficult>0</difficult>
    <bndbox>
      <xmin>1152.8893432617188</xmin>
      <ymin>359.18028259277344</ymin>
      <xmax>1174.1189575195312</xmax>
      <ymax>379.7002716064453</ymax>
    </bndbox>
  </object>
  <object>
    <name>xb_spore</name>
    <pose>Unspecified</pose>
    <truncated>0</truncated>
    <difficult>0</difficult>
    <bndbox>
      <xmin>1631.6654663085938</xmin>
      <ymin>684.1494140625</ymin>
      <xmax>1684.1035766601562</xmax>
      <ymax>733.58056640625</ymax>
    </bndbox>
  </object>
  <object>
    <name>shs_spore</name>
    <pose>Unspecified</pose>
    <truncated>0</truncated>
    <difficult>0</difficult>
    <bndbox>
      <xmin>1496.6218872070312</xmin>
      <ymin>583.1090698242188</ymin>
      <xmax>1519.0156860351562</xmax>
      <ymax>604.7656860351562</ymax>
    </bndbox>
  </object>
  <object>
    <name>dbb_spore</name>
    <pose>Unspecified</pose>
    <truncated>0</truncated>
    <difficult>0</difficult>
    <bndbox>
      <xmin>1768.1224365234375</xmin>
      <ymin>650.414794921875</ymin>
      <xmax>1836.1724853515625</xmax>
      <ymax>764.7890625</ymax>
    </bndbox>
  </object>
  <object>
    <name>xb_spore</name>
    <pose>Unspecified</pose>
    <truncated>0</truncated>
    <difficult>0</difficult>
    <bndbox>
      <xmin>1667.9884643554688</xmin>
      <ymin>646.1552124023438</ymin>
      <xmax>1710.3696899414062</xmax>
      <ymax>690.2032470703125</ymax>
    </bndbox>
  </object>
  <object>
    <name>xb_spore</name>
    <pose>Unspecified</pose>
    <truncated>0</truncated>
    <difficult>0</difficult>
    <bndbox>
      <xmin>1645.2453002929688</xmin>
      <ymin>737.726806640625</ymin>
      <xmax>1683.8065795898438</xmax>
      <ymax>769.7138671875</ymax>
    </bndbox>
  </object>
  <object>
    <name>shs_spore</name>
    <pose>Unspecified</pose>
    <truncated>0</truncated>
    <difficult>0</difficult>
    <bndbox>
      <xmin>182.5870646766169</xmin>
      <ymin>800.9950248756218</ymin>
      <xmax>203.4825870646766</xmax>
      <ymax>818.9054726368158</ymax>
    </bndbox>
  </object>
</annotation>
