<?xml version="1.0" ?>
<annotation>
  <folder>E:\spore\´ó°ßË¿ºÚËëÐâ²¡»ìºÏ\Annotations</folder>
  <filename>mixed_0503.jpg</filename>
  <size>
    <width>1920</width>
    <height>1080</height>
    <depth>3</depth>
  </size>
  <object>
    <name>dbb_spore</name>
    <pose>Unspecified</pose>
    <truncated>0</truncated>
    <difficult>0</difficult>
    <bndbox>
      <xmin>582.4286499023438</xmin>
      <ymin>594.9347534179688</ymin>
      <xmax>708.396240234375</xmax>
      <ymax>687.6417846679688</ymax>
    </bndbox>
  </object>
  <object>
    <name>shs_spore</name>
    <pose>Unspecified</pose>
    <truncated>0</truncated>
    <difficult>0</difficult>
    <bndbox>
      <xmin>526.3775024414062</xmin>
      <ymin>10.905303955078125</ymin>
      <xmax>550.1098022460938</xmax>
      <ymax>33.067657470703125</ymax>
    </bndbox>
  </object>
  <object>
    <name>xb_spore</name>
    <pose>Unspecified</pose>
    <truncated>0</truncated>
    <difficult>0</difficult>
    <bndbox>
      <xmin>245.53324127197266</xmin>
      <ymin>667.3577270507812</ymin>
      <xmax>290.8902053833008</xmax>
      <ymax>714.4147338867188</ymax>
    </bndbox>
  </object>
  <object>
    <name>xb_spore</name>
    <pose>Unspecified</pose>
    <truncated>0</truncated>
    <difficult>0</difficult>
    <bndbox>
      <xmin>708.3983001708984</xmin>
      <ymin>969.6154174804688</ymin>
      <xmax>755.9355010986328</xmax>
      <ymax>1017.7267456054688</ymax>
    </bndbox>
  </object>
  <object>
    <name>shs_spore</name>
    <pose>Unspecified</pose>
    <truncated>0</truncated>
    <difficult>0</difficult>
    <bndbox>
      <xmin>482.93115234375</xmin>
      <ymin>373.1766357421875</ymin>
      <xmax>507.5970153808594</xmax>
      <ymax>396.3955078125</ymax>
    </bndbox>
  </object>
  <object>
    <name>shs_spore</name>
    <pose>Unspecified</pose>
    <truncated>0</truncated>
    <difficult>0</difficult>
    <bndbox>
      <xmin>1628.92529296875</xmin>
      <ymin>207.989501953125</ymin>
      <xmax>1651.825927734375</xmax>
      <ymax>229.046630859375</ymax>
    </bndbox>
  </object>
  <object>
    <name>shs_spore</name>
    <pose>Unspecified</pose>
    <truncated>0</truncated>
    <difficult>0</difficult>
    <bndbox>
      <xmin>784.0237426757812</xmin>
      <ymin>611.600830078125</ymin>
      <xmax>806.7727661132812</xmax>
      <ymax>632.9879150390625</ymax>
    </bndbox>
  </object>
  <object>
    <name>xb_spore</name>
    <pose>Unspecified</pose>
    <truncated>0</truncated>
    <difficult>0</difficult>
    <bndbox>
      <xmin>821.31884765625</xmin>
      <ymin>774.25927734375</ymin>
      <xmax>863.7125244140625</xmax>
      <ymax>815.9285888671875</ymax>
    </bndbox>
  </object>
  <object>
    <name>shs_spore</name>
    <pose>Unspecified</pose>
    <truncated>0</truncated>
    <difficult>0</difficult>
    <bndbox>
      <xmin>1697.2283935546875</xmin>
      <ymin>133.0579376220703</ymin>
      <xmax>1719.6591796875</xmax>
      <ymax>154.2433319091797</ymax>
    </bndbox>
  </object>
  <object>
    <name>shs_spore</name>
    <pose>Unspecified</pose>
    <truncated>0</truncated>
    <difficult>0</difficult>
    <bndbox>
      <xmin>101.30433654785156</xmin>
      <ymin>163.84259033203125</ymin>
      <xmax>125.75164031982422</xmax>
      <ymax>186.0047607421875</ymax>
    </bndbox>
  </object>
  <object>
    <name>xb_spore</name>
    <pose>Unspecified</pose>
    <truncated>0</truncated>
    <difficult>0</difficult>
    <bndbox>
      <xmin>865.9085083007812</xmin>
      <ymin>774.17578125</ymin>
      <xmax>915.7886352539062</xmax>
      <ymax>818.022216796875</ymax>
    </bndbox>
  </object>
  <object>
    <name>shs_spore</name>
    <pose>Unspecified</pose>
    <truncated>0</truncated>
    <difficult>0</difficult>
    <bndbox>
      <xmin>601.5975952148438</xmin>
      <ymin>590.7262573242188</ymin>
      <xmax>628.5258178710938</xmax>
      <ymax>611.1626586914062</ymax>
    </bndbox>
  </object>
  <object>
    <name>xb_spore</name>
    <pose>Unspecified</pose>
    <truncated>0</truncated>
    <difficult>0</difficult>
    <bndbox>
      <xmin>568.9198608398438</xmin>
      <ymin>941.8706359863281</ymin>
      <xmax>610.3626708984375</xmax>
      <ymax>989.1221008300781</ymax>
    </bndbox>
  </object>
  <object>
    <name>xb_spore</name>
    <pose>Unspecified</pose>
    <truncated>0</truncated>
    <difficult>0</difficult>
    <bndbox>
      <xmin>324.0692138671875</xmin>
      <ymin>786.9353942871094</ymin>
      <xmax>367.5538330078125</xmax>
      <ymax>832.6222229003906</ymax>
    </bndbox>
  </object>
  <object>
    <name>xb_spore</name>
    <pose>Unspecified</pose>
    <truncated>0</truncated>
    <difficult>0</difficult>
    <bndbox>
      <xmin>285.5018005371094</xmin>
      <ymin>822.9927978515625</ymin>
      <xmax>346.24461364746094</xmax>
      <ymax>875.1185302734375</ymax>
    </bndbox>
  </object>
  <object>
    <name>shs_spore</name>
    <pose>Unspecified</pose>
    <truncated>0</truncated>
    <difficult>0</difficult>
    <bndbox>
      <xmin>119.3280258178711</xmin>
      <ymin>623.2261962890625</ymin>
      <xmax>142.5999755859375</xmax>
      <ymax>646.3714599609375</ymax>
    </bndbox>
  </object>
  <object>
    <name>xb_spore</name>
    <pose>Unspecified</pose>
    <truncated>0</truncated>
    <difficult>0</difficult>
    <bndbox>
      <xmin>0.0</xmin>
      <ymin>11.000198364257812</ymin>
      <xmax>23.357999324798584</xmax>
      <ymax>56.83241271972656</ymax>
    </bndbox>
  </object>
  <object>
    <name>xb_spore</name>
    <pose>Unspecified</pose>
    <truncated>0</truncated>
    <difficult>0</difficult>
    <bndbox>
      <xmin>0.0</xmin>
      <ymin>87.521484375</ymin>
      <xmax>16.84791898727417</xmax>
      <ymax>118.65582275390625</ymax>
    </bndbox>
  </object>
</annotation>
