<?xml version="1.0" ?>
<annotation>
  <folder>E:\spore\´ó°ßË¿ºÚËëÐâ²¡»ìºÏ\Annotations</folder>
  <filename>mixed_0745.jpg</filename>
  <size>
    <width>1920</width>
    <height>1200</height>
    <depth>3</depth>
  </size>
  <object>
    <name>dbb_spore</name>
    <pose>Unspecified</pose>
    <truncated>0</truncated>
    <difficult>0</difficult>
    <bndbox>
      <xmin>1341.39111328125</xmin>
      <ymin>231.8068084716797</ymin>
      <xmax>1507.7926025390625</xmax>
      <ymax>305.35276794433594</ymax>
    </bndbox>
  </object>
  <object>
    <name>dbb_spore</name>
    <pose>Unspecified</pose>
    <truncated>0</truncated>
    <difficult>0</difficult>
    <bndbox>
      <xmin>534.7911071777344</xmin>
      <ymin>384.65528869628906</ymin>
      <xmax>583.2214965820312</xmax>
      <ymax>520.6558227539062</ymax>
    </bndbox>
  </object>
  <object>
    <name>dbb_spore</name>
    <pose>Unspecified</pose>
    <truncated>0</truncated>
    <difficult>0</difficult>
    <bndbox>
      <xmin>263.21278381347656</xmin>
      <ymin>629.5020446777344</ymin>
      <xmax>426.8744659423828</xmax>
      <ymax>700.9476013183594</ymax>
    </bndbox>
  </object>
  <object>
    <name>xb_spore</name>
    <pose>Unspecified</pose>
    <truncated>0</truncated>
    <difficult>0</difficult>
    <bndbox>
      <xmin>322.05338287353516</xmin>
      <ymin>730.3515930175781</ymin>
      <xmax>364.58068084716797</xmax>
      <ymax>770.5469055175781</ymax>
    </bndbox>
  </object>
  <object>
    <name>dbb_spore</name>
    <pose>Unspecified</pose>
    <truncated>0</truncated>
    <difficult>0</difficult>
    <bndbox>
      <xmin>627.2005004882812</xmin>
      <ymin>381.14378356933594</ymin>
      <xmax>677.7388916015625</xmax>
      <ymax>536.8917846679688</ymax>
    </bndbox>
  </object>
  <object>
    <name>xb_spore</name>
    <pose>Unspecified</pose>
    <truncated>0</truncated>
    <difficult>0</difficult>
    <bndbox>
      <xmin>328.3505859375</xmin>
      <ymin>775.0828857421875</ymin>
      <xmax>367.0426025390625</xmax>
      <ymax>816.7620849609375</ymax>
    </bndbox>
  </object>
  <object>
    <name>shs_spore</name>
    <pose>Unspecified</pose>
    <truncated>0</truncated>
    <difficult>0</difficult>
    <bndbox>
      <xmin>152.16078186035156</xmin>
      <ymin>746.4197387695312</ymin>
      <xmax>176.19442749023438</xmax>
      <ymax>767.4266967773438</ymax>
    </bndbox>
  </object>
  <object>
    <name>xb_spore</name>
    <pose>Unspecified</pose>
    <truncated>0</truncated>
    <difficult>0</difficult>
    <bndbox>
      <xmin>319.4907531738281</xmin>
      <ymin>886.0563354492188</ymin>
      <xmax>358.73199462890625</xmax>
      <ymax>928.6265258789062</ymax>
    </bndbox>
  </object>
  <object>
    <name>xb_spore</name>
    <pose>Unspecified</pose>
    <truncated>0</truncated>
    <difficult>0</difficult>
    <bndbox>
      <xmin>380.5549621582031</xmin>
      <ymin>840.9135131835938</ymin>
      <xmax>419.611083984375</xmax>
      <ymax>879.5692749023438</ymax>
    </bndbox>
  </object>
  <object>
    <name>xb_spore</name>
    <pose>Unspecified</pose>
    <truncated>0</truncated>
    <difficult>0</difficult>
    <bndbox>
      <xmin>253.9844970703125</xmin>
      <ymin>917.4354858398438</ymin>
      <xmax>292.49725341796875</xmax>
      <ymax>953.4768676757812</ymax>
    </bndbox>
  </object>
  <object>
    <name>xb_spore</name>
    <pose>Unspecified</pose>
    <truncated>0</truncated>
    <difficult>0</difficult>
    <bndbox>
      <xmin>245.83511352539062</xmin>
      <ymin>746.09912109375</ymin>
      <xmax>282.8536834716797</xmax>
      <ymax>787.6505126953125</ymax>
    </bndbox>
  </object>
  <object>
    <name>shs_spore</name>
    <pose>Unspecified</pose>
    <truncated>0</truncated>
    <difficult>0</difficult>
    <bndbox>
      <xmin>1157.3309326171875</xmin>
      <ymin>910.5736999511719</ymin>
      <xmax>1178.8238525390625</xmax>
      <ymax>931.6262512207031</ymax>
    </bndbox>
  </object>
  <object>
    <name>xb_spore</name>
    <pose>Unspecified</pose>
    <truncated>0</truncated>
    <difficult>0</difficult>
    <bndbox>
      <xmin>292.5354309082031</xmin>
      <ymin>760.7755737304688</ymin>
      <xmax>324.41436767578125</xmax>
      <ymax>797.8086547851562</ymax>
    </bndbox>
  </object>
  <object>
    <name>xb_spore</name>
    <pose>Unspecified</pose>
    <truncated>0</truncated>
    <difficult>0</difficult>
    <bndbox>
      <xmin>224.5257339477539</xmin>
      <ymin>952.447998046875</ymin>
      <xmax>266.28128814697266</xmax>
      <ymax>1000.7684326171875</ymax>
    </bndbox>
  </object>
  <object>
    <name>shs_spore</name>
    <pose>Unspecified</pose>
    <truncated>0</truncated>
    <difficult>0</difficult>
    <bndbox>
      <xmin>1447.701416015625</xmin>
      <ymin>777.5108642578125</ymin>
      <xmax>1467.837158203125</xmax>
      <ymax>800.4744873046875</ymax>
    </bndbox>
  </object>
  <object>
    <name>xb_spore</name>
    <pose>Unspecified</pose>
    <truncated>0</truncated>
    <difficult>0</difficult>
    <bndbox>
      <xmin>151.3509979248047</xmin>
      <ymin>537.9459228515625</ymin>
      <xmax>172.23955535888672</xmax>
      <ymax>558.47900390625</ymax>
    </bndbox>
  </object>
  <object>
    <name>shs_spore</name>
    <pose>Unspecified</pose>
    <truncated>0</truncated>
    <difficult>0</difficult>
    <bndbox>
      <xmin>178.04132080078125</xmin>
      <ymin>150.9597930908203</ymin>
      <xmax>204.49282836914062</xmax>
      <ymax>175.13768005371094</ymax>
    </bndbox>
  </object>
  <object>
    <name>shs_spore</name>
    <pose>Unspecified</pose>
    <truncated>0</truncated>
    <difficult>0</difficult>
    <bndbox>
      <xmin>1567.3894023795401</xmin>
      <ymin>12.093891163771065</ymin>
      <xmax>1589.5334453482901</xmax>
      <ymax>35.63173296064607</ymax>
    </bndbox>
  </object>
  <object>
    <name>shs_spore</name>
    <pose>Unspecified</pose>
    <truncated>0</truncated>
    <difficult>0</difficult>
    <bndbox>
      <xmin>863.2283935546875</xmin>
      <ymin>47.626922607421875</ymin>
      <xmax>885.3627319335938</xmax>
      <ymax>68.35391235351562</ymax>
    </bndbox>
  </object>
  <object>
    <name>shs_spore</name>
    <pose>Unspecified</pose>
    <truncated>0</truncated>
    <difficult>0</difficult>
    <bndbox>
      <xmin>1554.9708251953125</xmin>
      <ymin>625.9556579589844</ymin>
      <xmax>1578.0523681640625</xmax>
      <ymax>646.4310607910156</ymax>
    </bndbox>
  </object>
  <object>
    <name>shs_spore</name>
    <pose>Unspecified</pose>
    <truncated>0</truncated>
    <difficult>0</difficult>
    <bndbox>
      <xmin>1684.7962646484375</xmin>
      <ymin>589.8178570480028</ymin>
      <xmax>1709.1807861328125</xmax>
      <ymax>612.4628765792528</ymax>
    </bndbox>
  </object>
  <object>
    <name>xb_spore</name>
    <pose>Unspecified</pose>
    <truncated>0</truncated>
    <difficult>0</difficult>
    <bndbox>
      <xmin>347.354736328125</xmin>
      <ymin>926.2377319335938</ymin>
      <xmax>374.0247802734375</xmax>
      <ymax>951.4400024414062</ymax>
    </bndbox>
  </object>
  <object>
    <name>shs_spore</name>
    <pose>Unspecified</pose>
    <truncated>0</truncated>
    <difficult>0</difficult>
    <bndbox>
      <xmin>1587.3890991210938</xmin>
      <ymin>865.0468139648438</ymin>
      <xmax>1605.3934936523438</xmax>
      <ymax>884.1762084960938</ymax>
    </bndbox>
  </object>
  <object>
    <name>shs_spore</name>
    <pose>Unspecified</pose>
    <truncated>0</truncated>
    <difficult>0</difficult>
    <bndbox>
      <xmin>1441.1861595039938</xmin>
      <ymin>796.3953729885727</ymin>
      <xmax>1462.6281761055563</xmax>
      <ymax>817.5814081448227</ymax>
    </bndbox>
  </object>
  <object>
    <name>shs_spore</name>
    <pose>Unspecified</pose>
    <truncated>0</truncated>
    <difficult>0</difficult>
    <bndbox>
      <xmin>239.75237274169922</xmin>
      <ymin>122.20500183105469</ymin>
      <xmax>264.17955780029297</xmax>
      <ymax>144.3728485107422</ymax>
    </bndbox>
  </object>
  <object>
    <name>xb_spore</name>
    <pose>Unspecified</pose>
    <truncated>0</truncated>
    <difficult>0</difficult>
    <bndbox>
      <xmin>344.40655517578125</xmin>
      <ymin>856.5181274414062</ymin>
      <xmax>384.390380859375</xmax>
      <ymax>890.0789794921875</ymax>
    </bndbox>
  </object>
  <object>
    <name>shs_spore</name>
    <pose>Unspecified</pose>
    <truncated>0</truncated>
    <difficult>0</difficult>
    <bndbox>
      <xmin>84.82394366197171</xmin>
      <ymin>7.042253521126761</ymin>
      <xmax>102.42957746478861</xmax>
      <ymax>23.591549295774648</ymax>
    </bndbox>
  </object>
  <object>
    <name>shs_spore</name>
    <pose>Unspecified</pose>
    <truncated>0</truncated>
    <difficult>0</difficult>
    <bndbox>
      <xmin>66.16197183098579</xmin>
      <ymin>2.1126760563380285</ymin>
      <xmax>83.76760563380269</xmax>
      <ymax>19.71830985915493</ymax>
    </bndbox>
  </object>
</annotation>
