<?xml version="1.0" ?>
<annotation>
  <folder>E:\spore\´ó°ßË¿ºÚËëÐâ²¡»ìºÏ\Annotations</folder>
  <filename>mixed_1118.jpg</filename>
  <size>
    <width>1920</width>
    <height>1200</height>
    <depth>3</depth>
  </size>
  <object>
    <name>dbb_spore</name>
    <pose>Unspecified</pose>
    <truncated>0</truncated>
    <difficult>0</difficult>
    <bndbox>
      <xmin>1101.211669921875</xmin>
      <ymin>543.4676513671875</ymin>
      <xmax>1227.1461181640625</xmax>
      <ymax>633.2867431640625</ymax>
    </bndbox>
  </object>
  <object>
    <name>dbb_spore</name>
    <pose>Unspecified</pose>
    <truncated>0</truncated>
    <difficult>0</difficult>
    <bndbox>
      <xmin>1299.2457275390625</xmin>
      <ymin>406.9603271484375</ymin>
      <xmax>1418.367919921875</xmax>
      <ymax>502.29327392578125</ymax>
    </bndbox>
  </object>
  <object>
    <name>shs_spore</name>
    <pose>Unspecified</pose>
    <truncated>0</truncated>
    <difficult>0</difficult>
    <bndbox>
      <xmin>122.3104133605957</xmin>
      <ymin>327.1064758300781</ymin>
      <xmax>145.3418312072754</xmax>
      <ymax>349.4466247558594</ymax>
    </bndbox>
  </object>
  <object>
    <name>dbb_spore</name>
    <pose>Unspecified</pose>
    <truncated>0</truncated>
    <difficult>0</difficult>
    <bndbox>
      <xmin>309.67735290527344</xmin>
      <ymin>443.17254638671875</ymin>
      <xmax>403.5846405029297</xmax>
      <ymax>504.48907470703125</ymax>
    </bndbox>
  </object>
  <object>
    <name>shs_spore</name>
    <pose>Unspecified</pose>
    <truncated>0</truncated>
    <difficult>0</difficult>
    <bndbox>
      <xmin>1792.482421875</xmin>
      <ymin>778.1654663085938</ymin>
      <xmax>1813.893310546875</xmax>
      <ymax>799.0464477539062</ymax>
    </bndbox>
  </object>
  <object>
    <name>shs_spore</name>
    <pose>Unspecified</pose>
    <truncated>0</truncated>
    <difficult>0</difficult>
    <bndbox>
      <xmin>1773.5972900390625</xmin>
      <ymin>784.9367065429688</ymin>
      <xmax>1793.9736328125</xmax>
      <ymax>805.9323120117188</ymax>
    </bndbox>
  </object>
  <object>
    <name>shs_spore</name>
    <pose>Unspecified</pose>
    <truncated>0</truncated>
    <difficult>0</difficult>
    <bndbox>
      <xmin>1815.2777777777776</xmin>
      <ymin>1117.1296296296296</ymin>
      <xmax>1838.8888888888887</xmax>
      <ymax>1137.5</ymax>
    </bndbox>
  </object>
</annotation>
